{
  "schema_version": 1,
  "corpus_id": "dataset-v3-production-corpus",
  "title": "Dataset v3 production corpus",
  "description": "Compact, diverse, production-style Online Boutique observability corpus for testing ranking, ML, NLP, AI, and agent approaches without overestimating performance.",
  "locked_baseline": "dataset-v2-final-production-v1",
  "development_stage": "dataset-first research benchmark expansion",
  "default_dataset_run_prefix": "dataset-v3-production-corpus",
  "aggregate_id_suffix": "aggregate",
  "holdout_id_suffix": "holdout",
  "collection_strategy": {
    "first_batch_runs": 2,
    "recommended_batch_runs": 2,
    "full_corpus_runs": 6,
    "why_batch_collection": "The corpus is intentionally compact enough to finish in a practical local run while preserving diverse fault families. Batch collection still lets us validate data quality and resume without discarding completed runs.",
    "expected_full_scale": {
      "dataset_runs": 6,
      "episodes": 69,
      "shadow_jira_issues": 39,
      "telemetry_windows": "500+",
      "per_run_ranking_pairs": "450+",
      "future_global_hard_negative_pairs": "2500+"
    }
  },
  "plans": [
    {
      "plan_alias": "compact-a",
      "plan_file": "deploy\\research-lab\\run-plans\\dataset-v3-diverse-compact-a.json",
      "repeat": 3,
      "purpose": "Latency, dependency outage, restart, Redis degradation, bad configuration, and near-miss coverage."
    },
    {
      "plan_alias": "compact-b",
      "plan_file": "deploy\\research-lab\\run-plans\\dataset-v3-diverse-compact-b.json",
      "repeat": 3,
      "purpose": "Service-diverse outages, frontend and Redis restarts, intermittent Redis failure, and noisy traffic coverage."
    }
  ],
  "benchmark_tracks": [
    {
      "track_id": "oracle_metadata_sanity",
      "description": "Uses clean labels and structured metadata to catch broken dataset contracts."
    },
    {
      "track_id": "noisy_jira_text",
      "description": "Uses delayed and noisy Jira-style issue text to evaluate production-like retrieval."
    },
    {
      "track_id": "raw_telemetry_only",
      "description": "Uses logs, metrics, traces, alerts, and Kubernetes evidence without Jira metadata leakage."
    },
    {
      "track_id": "global_hard_negative_retrieval",
      "description": "Future benchmark mode that pairs each Jira issue against candidates from all corpus runs."
    }
  ],
  "promotion_gates": {
    "raw_runs": "Every collected run must pass validate-dataset-run.ps1 with 0 errors.",
    "derived_outputs": "Every collected run should build ranking outputs with F1@1 and F1@3 present.",
    "aggregate_outputs": "Corpus aggregate and holdout reports must include MRR, Recall@1, Recall@3, F1@1, F1@3, and nDCG@3.",
    "quality_review": "Inspect failures before claiming model progress. Near misses and service-confusion errors are expected and useful."
  }
}
